LICENSE
MANIFEST.in
README.rst
setup.py
elfinder/.gitignore
elfinder/__init__.py
elfinder/__init__.pyc
elfinder/connector.py
elfinder/exceptions.py
elfinder/fields.py
elfinder/models.py
elfinder/urls.py
elfinder/views.py
elfinder/widgets.py
elfinder/conf/__init__.py
elfinder/conf/settings.py
elfinder/static/css/jquery.elfinder-widget.full.css
elfinder/static/elfinder/css/elfinder.full.css
elfinder/static/elfinder/css/elfinder.min.css
elfinder/static/elfinder/css/theme.css
elfinder/static/elfinder/img/arrows-active.png
elfinder/static/elfinder/img/arrows-normal.png
elfinder/static/elfinder/img/crop.gif
elfinder/static/elfinder/img/dialogs.png
elfinder/static/elfinder/img/icons-big.png
elfinder/static/elfinder/img/icons-small.png
elfinder/static/elfinder/img/logo.png
elfinder/static/elfinder/img/progress.gif
elfinder/static/elfinder/img/quicklook-bg.png
elfinder/static/elfinder/img/quicklook-icons.png
elfinder/static/elfinder/img/resize.png
elfinder/static/elfinder/img/spinner-mini.gif
elfinder/static/elfinder/img/toolbar.png
elfinder/static/elfinder/js/elfinder.full.js
elfinder/static/elfinder/js/elfinder.min.js
elfinder/static/elfinder/js/i18n/elfinder.LANG.js
elfinder/static/elfinder/js/i18n/elfinder.ar.js
elfinder/static/elfinder/js/i18n/elfinder.bg.js
elfinder/static/elfinder/js/i18n/elfinder.ca.js
elfinder/static/elfinder/js/i18n/elfinder.cs.js
elfinder/static/elfinder/js/i18n/elfinder.de.js
elfinder/static/elfinder/js/i18n/elfinder.el.js
elfinder/static/elfinder/js/i18n/elfinder.es.js
elfinder/static/elfinder/js/i18n/elfinder.fa.js
elfinder/static/elfinder/js/i18n/elfinder.fr.js
elfinder/static/elfinder/js/i18n/elfinder.hu.js
elfinder/static/elfinder/js/i18n/elfinder.it.js
elfinder/static/elfinder/js/i18n/elfinder.jp.js
elfinder/static/elfinder/js/i18n/elfinder.ko.js
elfinder/static/elfinder/js/i18n/elfinder.nl.js
elfinder/static/elfinder/js/i18n/elfinder.no.js
elfinder/static/elfinder/js/i18n/elfinder.pl.js
elfinder/static/elfinder/js/i18n/elfinder.pt_BR.js
yawd_elfinder.egg-info/PKG-INFO
yawd_elfinder.egg-info/SOURCES.txt
yawd_elfinder.egg-info/dependency_links.txt
yawd_elfinder.egg-info/requires.txt
yawd_elfinder.egg-info/top_level.txt